brainhance/__init__.py
brainhance/app.py
brainhance/my_io.py
brainhance/saved_models/1000BRAINS/saved_model.pb
brainhance/saved_models/1000BRAINS/variables/variables.data-00000-of-00001
brainhance/saved_models/1000BRAINS/variables/variables.index
brainhance/saved_models/Brain_Tumor/saved_model.pb
brainhance/saved_models/Brain_Tumor/variables/variables.data-00000-of-00001
brainhance/saved_models/Brain_Tumor/variables/variables.index
brainhance/saved_models/Generalist/saved_model.pb
brainhance/saved_models/Generalist/variables/variables.data-00000-of-00001
brainhance/saved_models/Generalist/variables/variables.index
brainhance/saved_models/dHCP/saved_model.pb
brainhance/saved_models/dHCP/variables/variables.data-00000-of-00001
brainhance/saved_models/dHCP/variables/variables.index
brainhance-0.0.1.dist-info/LICENSE
brainhance-0.0.1.dist-info/METADATA
brainhance-0.0.1.dist-info/WHEEL
brainhance-0.0.1.dist-info/entry_points.txt
brainhance-0.0.1.dist-info/top_level.txt
brainhance-0.0.1.dist-info/RECORD
