Metadata-Version: 2.1
Name: brainhance
Version: 0.0.1
Summary: Command-line tool to perform MRI upsampling via SRGANS
Home-page: https://github.com/LucasCampos/brainhance
Author: Lucas da Costa Campos
Author-email: lqccampos@gmail.com
License: UNKNOWN
Platform: UNKNOWN
Classifier: Programming Language :: Python :: 3
Classifier: License :: OSI Approved :: GNU General Public License v3 (GPLv3)
Classifier: Operating System :: OS Independent
Classifier: Topic :: Scientific/Engineering :: Medical Science Apps.
Requires-Python: >=3.6
License-File: LICENSE
Requires-Dist: numpy
Requires-Dist: nibabel
Requires-Dist: multiprocess
Requires-Dist: protobuf (==3.14.0)
Requires-Dist: tensorflow-gpu (==2.4.0)
